ZKBattleship/__init__.py
ZKBattleship/__main__.py
ZKBattleship/bitproof.py
ZKBattleship/board.py
ZKBattleship/pedersen.py
ZKBattleship/random_prime.py
ZKBattleship/stats.py
ZKBattleship-1.0.0.dist-info/LICENSE
ZKBattleship-1.0.0.dist-info/METADATA
ZKBattleship-1.0.0.dist-info/WHEEL
ZKBattleship-1.0.0.dist-info/top_level.txt
ZKBattleship-1.0.0.dist-info/RECORD
