Metadata-Version: 2.1
Name: ZKBattleship
Version: 1.0.0
Summary: Battleship with cryptographic protections and a zero-knowledge framework.
Home-page: https://github.com/SteelShredder/ZKBattleship
Author: Gavin Pai
Author-email: gavinpai@hotmail.com
License: UNKNOWN
Project-URL: Bug Tracker, https://github.com/SteelShredder/ZKBattleship/issues
Platform: UNKNOWN
Classifier: Programming Language :: Python :: 3.9
Classifier: License :: OSI Approved :: GNU General Public License v3 or later (GPLv3+)
Classifier: Operating System :: Microsoft :: Windows :: Windows 10
Classifier: Natural Language :: English
Classifier: Topic :: Security :: Cryptography
Requires-Python: >=3.8
